renertpy/__init__.py
renertpy/all.py
renertpy/colors.py
renertpy/data.py
renertpy/dicts.py
renertpy/display.py
renertpy/list_audio.py
renertpy/list_plots.py
renertpy/turtle.py
renertpy/turtle_impl.py
renertpy/utils.py
renertpy/version.py
renertpy/data/balls.jpg
renertpy/data/butterfly.jpg
renertpy/data/kitten.jpg
renertpy/data/llama.jpg
renertpy/data/paints.jpg
renertpy/data/panda.jpg
renertpy/data/parrot.jpg
renertpy/data/puppy.jpg
renertpy/data/rose.jpg
renertpy/data/sloth.jpg
renertpy/data/tulips.jpg
renertpy/moby/__init__.py
renertpy/moby/adjectives_b64.py
renertpy/moby/adverbs_b64.py
renertpy/moby/nouns_b64.py
renertpy/moby/verbs_b64.py
renertpy-0.6.0.dist-info/METADATA
renertpy-0.6.0.dist-info/WHEEL
renertpy-0.6.0.dist-info/top_level.txt
renertpy-0.6.0.dist-info/RECORD
