Metadata-Version: 2.4
Name: renertpy
Version: 0.6.0
Summary: Collection of functions used to teach Python at Renert School
Home-page: https://github.com/agordon/renertpy
Author: Assaf Gordon
Author-email: AssafGordon@gmail.com
License: BSD
Keywords: jupyter
Classifier: Development Status :: 3 - Alpha
Classifier: License :: OSI Approved :: BSD License
Requires-Dist: numpy
Requires-Dist: ipycanvas
Requires-Dist: pillow
Dynamic: author
Dynamic: author-email
Dynamic: classifier
Dynamic: description
Dynamic: home-page
Dynamic: keywords
Dynamic: license
Dynamic: requires-dist
Dynamic: summary
